{
  "version": 3,
  "middleware": {
    "/": {
      "files": [
        "server/edge/chunks/_2bfa59cf._.js",
        "server/edge/chunks/[root-of-the-server]__140a91e5._.js",
        "server/edge/chunks/turbopack-edge-wrapper_937effaf.js"
      ],
      "name": "middleware",
      "page": "/",
      "matchers": [
        {
          "regexp": "^(?:\\/(_next\\/data\\/[^/]{1,}))?\\/dashboard(?:\\/((?:[^\\/#\\?]+?)(?:\\/(?:[^\\/#\\?]+?))*))?(\\\\.json)?[\\/#\\?]?$",
          "originalSource": "/dashboard/:path*"
        }
      ],
      "wasm": [],
      "assets": [],
      "env": {
        "__NEXT_BUILD_ID": "development",
        "NEXT_SERVER_ACTIONS_ENCRYPTION_KEY": "/PnsZ1+Qms7+n+wMXwWhdQrs5xN4qmSSndwqw25miX4=",
        "__NEXT_PREVIEW_MODE_ID": "e4c959cd3ca65f8e13dfec3ec55a91a9",
        "__NEXT_PREVIEW_MODE_ENCRYPTION_KEY": "aa4c2c3b75f4d63e72cac4cc56c7ec38d4380ca7cf6519db7391910881fa8eb4",
        "__NEXT_PREVIEW_MODE_SIGNING_KEY": "f99f387a4c0568ce5999f1f2a57e01db92365eff8e8f5c0b27910506b2c9f099"
      }
    }
  },
  "sortedMiddleware": [
    "/"
  ],
  "functions": {}
}